sciby/__init__.py
sciby/calc_expr.cp312-win_amd64.pyd
sciby/process.cp312-win_amd64.pyd
sciby/service.cp312-win_amd64.pyd
sciby/algorithm/__init__.py
sciby/algorithm/binning.cp312-win_amd64.pyd
sciby/algorithm/correlate.cp312-win_amd64.pyd
sciby/algorithm/distance.cp312-win_amd64.pyd
sciby/algorithm/entropy.cp312-win_amd64.pyd
sciby/algorithm/gene.cp312-win_amd64.pyd
sciby/algorithm/kdtree.cp312-win_amd64.pyd
sciby/algorithm/linear_regression.cp312-win_amd64.pyd
sciby/algorithm/metric.cp312-win_amd64.pyd
sciby/algorithm/pca.cp312-win_amd64.pyd
sciby/algorithm/similar.cp312-win_amd64.pyd
sciby/algorithm/trie.cp312-win_amd64.pyd
sciby/algorithm/weight.cp312-win_amd64.pyd
sciby/associate/__init__.py
sciby/associate/apriori.cp312-win_amd64.pyd
sciby/associate/rule_merge.cp312-win_amd64.pyd
sciby/associate/sbar.cp312-win_amd64.pyd
sciby/cluster/__init__.py
sciby/cluster/bestkmeans.cp312-win_amd64.pyd
sciby/cluster/fourstep.cp312-win_amd64.pyd
sciby/cluster/seqsim.cp312-win_amd64.pyd
sciby/data/brand.json
sciby/data/division.json
sciby/data/ethnic.json
sciby/data/trade.json
sciby/graph/__init__.py
sciby/graph/louvain.cp312-win_amd64.pyd
sciby/image/__init__.py
sciby/image/assess.cp312-win_amd64.pyd
sciby/image/edge.cp312-win_amd64.pyd
sciby/image/feature.cp312-win_amd64.pyd
sciby/image/kernel.cp312-win_amd64.pyd
sciby/image/process.cp312-win_amd64.pyd
sciby/image/threshold.cp312-win_amd64.pyd
sciby/language/__init__.py
sciby/language/cut.cp312-win_amd64.pyd
sciby/language/document.cp312-win_amd64.pyd
sciby/language/entity.cp312-win_amd64.pyd
sciby/language/hash.cp312-win_amd64.pyd
sciby/language/keyword.cp312-win_amd64.pyd
sciby/language/longest_common.cp312-win_amd64.pyd
sciby/language/process.cp312-win_amd64.pyd
sciby/language/tagging.cp312-win_amd64.pyd
sciby/language/tokenize.cp312-win_amd64.pyd
sciby/language/topic.cp312-win_amd64.pyd
sciby/language/vocab.cp312-win_amd64.pyd
sciby/neuralnet/__init__.py
sciby/neuralnet/activate.cp312-win_amd64.pyd
sciby-0.1.0.dist-info/METADATA
sciby-0.1.0.dist-info/WHEEL
sciby-0.1.0.dist-info/top_level.txt
sciby-0.1.0.dist-info/RECORD
