Metadata-Version: 2.1
Name: sciby
Version: 0.1.0
Home-page: 
Author: 
Author-email: 
License: Licence
Platform: any
Requires-Dist: numpy >=1.24.0
Requires-Dist: scipy >=1.12.0
Requires-Dist: pandas >=2.2.0
